lbftd/__init__.py
lbftd/evalGibbs.py
lbftd/loadGibbs.py
lbftd/statevars.py
mlbspline/__init__.py
mlbspline/eval.py
mlbspline/load.py
seafreeze/SeaFreeze_Gibbs_VII_NaCl.mat
seafreeze/__init__.py
seafreeze/seafreeze.py
SeaFreeze-1.0.0.dist-info/LICENSE.txt
SeaFreeze-1.0.0.dist-info/METADATA
SeaFreeze-1.0.0.dist-info/WHEEL
SeaFreeze-1.0.0.dist-info/top_level.txt
SeaFreeze-1.0.0.dist-info/RECORD
