Metadata-Version: 2.1
Name: SeaFreeze
Version: 1.0.0
Summary: Thermodynamic properties of the phases of H2O and NaCl (aq)
Home-page: https://github.com/Bjournaux/SeaFreeze
Download-URL: https://pypi.org/project/SeaFreeze/
Author: Baptiste Journaux
Author-email: bjournau@uw.edu
Classifier: Programming Language :: Python :: 3.11
Classifier: License :: OSI Approved :: GNU General Public License v3 (GPLv3)
Classifier: Operating System :: OS Independent
License-File: LICENSE.txt
Requires-Dist: h5py >=3.10
Requires-Dist: hdf5storage >=0.1.19
Requires-Dist: numpy >=1.26.3
Requires-Dist: scipy >=1.12
Requires-Dist: psutil >=5.9.8
